<?xml version="1.1" encoding="UTF-8"?>
<pipeline>
   <elements>
      <add>
         <element>
            <id>Source</id>
            <type>Source</type>
         </element>
         <element>
            <id>xmlParser</id>
            <type>XMLParser</type>
         </element>
         <element>
            <id>stateFilter</id>
            <type>StateFilter</type>
         </element>
      </add>
   </elements>
   <properties>
      <add>
         <property>
            <element>stateFilter</element>
            <name>stateDoc</name>
            <value>
               <entity>
                  <type>StateStore</type>
                  <uuid>b61694cd-fa11-4d5e-962c-74b86e5126ef</uuid>
                  <name>State Store</name>
               </entity>
            </value>
         </property>
      </add>
   </properties>
   <links>
      <add>
         <link>
            <from>Source</from>
            <to>xmlParser</to>
         </link>
         <link>
            <from>xmlParser</from>
            <to>stateFilter</to>
         </link>
      </add>
   </links>
</pipeline>
